Code/CGESystem.py
Code/Calibration.py
Code/Consumer.py
Code/MacroEconomy.py
Code/Producer.py
Code/Run.py
Code/__init__.py
SimplifiedCGE_CHN_0.1-0.1.dist-info/METADATA
SimplifiedCGE_CHN_0.1-0.1.dist-info/WHEEL
SimplifiedCGE_CHN_0.1-0.1.dist-info/entry_points.txt
SimplifiedCGE_CHN_0.1-0.1.dist-info/top_level.txt
SimplifiedCGE_CHN_0.1-0.1.dist-info/RECORD
